tfds/__init__.py
tfds/decorators.py
tfds/log.py
tfds/plotting.py
tfds-0.3.dist-info/METADATA
tfds-0.3.dist-info/WHEEL
tfds-0.3.dist-info/RECORD
