Metadata-Version: 2.1
Name: tfds
Version: 0.3
Summary: 
Author: tdfalc
Author-email: tomdfalc@gmail.com
Requires-Python: >=3.11,<3.13
Classifier: Programming Language :: Python :: 3
Classifier: Programming Language :: Python :: 3.11
Classifier: Programming Language :: Python :: 3.12
Requires-Dist: black (>=24.8.0,<25.0.0)
Requires-Dist: cloudpickle (>=3.0.0,<4.0.0)
Requires-Dist: coveralls (>=4.0.1,<5.0.0)
Requires-Dist: matplotlib (>=3.9.1.post1,<4.0.0)
Requires-Dist: pytest (>=8.3.2,<9.0.0)
Requires-Dist: pytest-cov (>=5.0.0,<6.0.0)
